{"comments":null,"declarations":[{"children":[],"comments":"A `Behavior` which reports the current mouse position, if it is known.\n","info":{"declType":"value","type":{"annotation":[],"contents":[{"annotation":[],"contents":[{"annotation":[],"contents":[["Prim"],"Function"],"tag":"TypeConstructor"},{"annotation":[],"contents":[["FRP","Event","Mouse"],"Mouse"],"tag":"TypeConstructor"}],"tag":"TypeApp"},{"annotation":[],"contents":[{"annotation":[],"contents":[["FRP","Behavior"],"Behavior"],"tag":"TypeConstructor"},{"annotation":[],"contents":{"annotation":[],"contents":[{"annotation":[],"contents":[["Data","Maybe"],"Maybe"],"tag":"TypeConstructor"},{"annotation":[],"contents":[{"annotation":[],"contents":[["Prim"],"Record"],"tag":"TypeConstructor"},{"annotation":[],"contents":["x",{"annotation":[],"contents":[["Prim"],"Int"],"tag":"TypeConstructor"},{"annotation":[],"contents":["y",{"annotation":[],"contents":[["Prim"],"Int"],"tag":"TypeConstructor"},{"annotation":[],"tag":"REmpty"}],"tag":"RCons"}],"tag":"RCons"}],"tag":"TypeApp"}],"tag":"TypeApp"},"tag":"ParensInType"}],"tag":"TypeApp"}],"tag":"TypeApp"}},"kind":null,"sourceSpan":{"end":[14,61],"name":".spago/p/hyrule-2.3.8/src/FRP/Behavior/Mouse.purs","start":[14,1]},"title":"position"},{"children":[],"comments":"A `Behavior` which reports the mouse buttons which are currently pressed.\n","info":{"declType":"value","type":{"annotation":[],"contents":[{"annotation":[],"contents":[{"annotation":[],"contents":[["Prim"],"Function"],"tag":"TypeConstructor"},{"annotation":[],"contents":[["FRP","Event","Mouse"],"Mouse"],"tag":"TypeConstructor"}],"tag":"TypeApp"},{"annotation":[],"contents":[{"annotation":[],"contents":[["FRP","Behavior"],"Behavior"],"tag":"TypeConstructor"},{"annotation":[],"contents":{"annotation":[],"contents":[{"annotation":[],"contents":[["Data","Set"],"Set"],"tag":"TypeConstructor"},{"annotation":[],"contents":[["Prim"],"Int"],"tag":"TypeConstructor"}],"tag":"TypeApp"},"tag":"ParensInType"}],"tag":"TypeApp"}],"tag":"TypeApp"}},"kind":null,"sourceSpan":{"end":[18,43],"name":".spago/p/hyrule-2.3.8/src/FRP/Behavior/Mouse.purs","start":[18,1]},"title":"buttons"}],"name":"FRP.Behavior.Mouse","reExports":[]}